{"type": "Feature", "id": 12515653, "geometry": {"type": "Point", "coordinates": [120.358299, 17.5564]}, "properties": {"woe:id": 12515653, "woe:parent_id": 1200033, "woe:name": "Vigan Airport", "woe:placetype": 14, "woe:placetype_name": "Airport", "woe:lang": "ENG", "iso:country": "PH", "meta:provider": ["geoplanet:7.3.1", "geoplanet:7.3.2", "geoplanet:7.4.0", "geoplanet:7.4.1", "geoplanet:7.5.1", "geoplanet:7.5.2", "geoplanet:7.6.0", "geoplanet:7.8.1", "geoplanet:7.9.0", "geoplanet:7.10.0", "geoplanet:8.0.0", "woeplanet:8.0.0"], "meta:indexed": "2020-08-20T21:02:16.333842", "meta:updated": "2020-10-14T11:45:51.059031", "woe:hierarchy": {"continent": 24865671, "country": 23424934, "town": 0, "planet": 1, "county": 2346684, "suburb": 0, "state": 23424724, "region": 0, "localadmin": 0}, "woe:timezone_id": 28350843, "woe:hash": "wejefu41rwhm", "woe:centroid": [120.358299, 17.5564], "geom:latitude": 17.5564, "geom:longitude": 120.358299, "geom:hash": "wejefu41rwhm", "woe:latitude": 17.5564, "geom:centroid": [120.358299, 17.5564], "woe:longitude": 120.358299, "woe:repo": "woeplanet-airport-ph", "geom:area": 0.0, "woe:scale": 19}}