{"type": "Feature", "id": 12515628, "geometry": {"type": "Point", "coordinates": [120.240601, 16.0329]}, "properties": {"woe:id": 12515628, "woe:parent_id": 1178486, "woe:name": "Lingayen Airport", "woe:placetype": 14, "woe:placetype_name": "Airport", "woe:lang": "ENG", "iso:country": "PH", "meta:provider": ["geoplanet:7.3.1", "geoplanet:7.3.2", "geoplanet:7.4.0", "geoplanet:7.4.1", "geoplanet:7.5.1", "geoplanet:7.5.2", "geoplanet:7.6.0", "geoplanet:7.8.1", "geoplanet:7.9.0", "geoplanet:7.10.0", "geoplanet:8.0.0", "woeplanet:8.0.0"], "meta:indexed": "2020-08-20T21:02:16.316459", "meta:updated": "2020-10-14T11:45:51.074654", "woe:hierarchy": {"continent": 24865671, "country": 23424934, "town": 0, "planet": 1, "county": 2346705, "suburb": 0, "state": 23424724, "region": 0, "localadmin": 0}, "woe:timezone_id": 28350843, "woe:hash": "wdve0nsw3j4m", "woe:centroid": [120.240601, 16.0329], "geom:latitude": 16.0329, "geom:longitude": 120.240601, "geom:hash": "wdve0nsw3j4m", "woe:latitude": 16.0329, "geom:centroid": [120.240601, 16.0329], "woe:longitude": 120.240601, "woe:repo": "woeplanet-airport-ph", "geom:area": 0.0, "woe:scale": 19}}