{"type": "Feature", "id": 12515626, "geometry": {"type": "Point", "coordinates": [120.529404, 18.179701]}, "properties": {"woe:id": 12515626, "woe:parent_id": 1200031, "woe:name": "Laoag International Airport", "woe:placetype": 14, "woe:placetype_name": "Airport", "woe:lang": "ENG", "iso:country": "PH", "meta:provider": ["geoplanet:7.3.1", "geoplanet:7.3.2", "geoplanet:7.4.0", "geoplanet:7.4.1", "geoplanet:7.5.1", "geoplanet:7.5.2", "geoplanet:7.6.0", "geoplanet:7.8.1", "geoplanet:7.9.0", "geoplanet:7.10.0", "geoplanet:8.0.0", "woeplanet:8.0.0"], "meta:indexed": "2020-08-20T21:02:16.314892", "woe:alias_ENG_V": ["LAO Airport", "LAO"], "meta:updated": "2020-10-14T11:45:51.080102", "woe:hierarchy": {"continent": 24865671, "country": 23424934, "town": 0, "planet": 1, "county": 2346683, "suburb": 0, "state": 23424724, "region": 0, "localadmin": 0}, "woe:timezone_id": 28350843, "woe:hash": "wejxqtwb6tvs", "woe:centroid": [120.529404, 18.179701], "geom:latitude": 18.179701, "geom:longitude": 120.529404, "geom:hash": "wejxqtwb6tvs", "woe:latitude": 18.179701, "geom:centroid": [120.529404, 18.179701], "woe:longitude": 120.529404, "woe:repo": "woeplanet-airport-ph", "geom:area": 0.0, "woe:scale": 19}}