{"type": "Feature", "id": 12515611, "properties": {"woe:id": 12515611, "woe:parent_id": 1199879, "woe:name": "Daniel Z Romualdez Airport", "woe:placetype": 14, "woe:placetype_name": "Airport", "woe:lang": "ENG", "iso:country": "PH", "meta:provider": ["geoplanet:7.3.1", "geoplanet:7.3.2", "geoplanet:7.4.0", "geoplanet:7.4.1", "geoplanet:7.5.1", "geoplanet:7.5.2", "geoplanet:7.6.0", "geoplanet:7.8.1", "geoplanet:7.9.0", "geoplanet:7.10.0", "geoplanet:8.0.0", "woeplanet:8.0.0"], "meta:indexed": "2020-08-20T21:02:16.302491", "woe:alias_ENG_V": ["TAC Airport", "TAC", "Daniel Z Romualdez"], "meta:updated": "2020-08-22T02:49:29.439397", "woe:hierarchy": {"continent": 24865671, "country": 23424934, "town": 0, "planet": 1, "county": 2346692, "suburb": 0, "state": 23424723, "region": 0, "localadmin": 0}, "woe:timezone_id": 28350843, "woe:hash": "wcbzuuncd6f4", "woe:centroid": [125.022797, 11.2283], "geom:latitude": 11.2283, "geom:longitude": 125.022797, "geom:hash": "wcbzuuncd6f4", "woe:latitude": 11.2283, "geom:centroid": [125.022797, 11.2283], "woe:longitude": 125.022797, "woe:repo": "woeplanet-airport-ph"}, "geometry": {"coordinates": [125.022797, 11.2283], "type": "Point"}}