{"type": "Feature", "id": 12515636, "properties": {"woe:id": 12515636, "woe:parent_id": 1187711, "woe:name": "Naga Airport", "woe:placetype": 14, "woe:placetype_name": "Airport", "woe:lang": "ENG", "iso:country": "PH", "meta:provider": ["geoplanet:7.3.1", "geoplanet:7.3.2", "geoplanet:7.4.0", "geoplanet:7.4.1", "geoplanet:7.5.1", "geoplanet:7.5.2", "geoplanet:7.6.0", "geoplanet:7.8.1", "geoplanet:7.9.0", "geoplanet:7.10.0", "geoplanet:8.0.0", "woeplanet:8.0.0"], "meta:indexed": "2020-08-20T21:02:16.321461", "woe:alias_ENG_V": ["WNP Airport", "WNP"], "meta:updated": "2020-08-22T02:49:29.447239", "woe:hierarchy": {"continent": 24865671, "country": 23424934, "town": 0, "planet": 1, "county": 2346671, "suburb": 0, "state": 23424720, "region": 0, "localadmin": 0}, "woe:timezone_id": 28350843, "woe:hash": "wdrtm16rpjev", "woe:centroid": [123.269997, 13.5872], "geom:latitude": 13.5872, "geom:longitude": 123.269997, "geom:hash": "wdrtm16rpjev", "woe:latitude": 13.5872, "geom:centroid": [123.269997, 13.5872], "woe:longitude": 123.269997, "woe:repo": "woeplanet-airport-ph"}, "geometry": {"coordinates": [123.269997, 13.5872], "type": "Point"}}