{"type": "Feature", "id": 12515620, "geometry": {"type": "Point", "coordinates": [124.208298, 8.15]}, "properties": {"woe:id": 12515620, "woe:parent_id": 1161444, "woe:name": "Iligan Airport", "woe:placetype": 14, "woe:placetype_name": "Airport", "woe:lang": "ENG", "iso:country": "PH", "meta:provider": ["geoplanet:7.3.1", "geoplanet:7.3.2", "geoplanet:7.4.0", "geoplanet:7.4.1", "geoplanet:7.5.1", "geoplanet:7.5.2", "geoplanet:7.6.0", "geoplanet:7.8.1", "geoplanet:7.9.0", "geoplanet:7.10.0", "geoplanet:8.0.0", "woeplanet:8.0.0"], "meta:indexed": "2020-08-20T21:02:16.309874", "woe:alias_ENG_V": ["IGN Airport", "IGN"], "meta:updated": "2020-10-14T11:45:51.070231", "woe:hierarchy": {"continent": 24865671, "country": 23424934, "town": 0, "planet": 1, "county": 2346689, "suburb": 0, "state": 23424730, "region": 0, "localadmin": 0}, "woe:timezone_id": 28350843, "woe:hash": "wc2q67ttpn5g", "woe:centroid": [124.208298, 8.15], "geom:latitude": 8.15, "geom:longitude": 124.208298, "geom:hash": "wc2q67ttpn5g", "woe:latitude": 8.15, "geom:centroid": [124.208298, 8.15], "woe:longitude": 124.208298, "woe:repo": "woeplanet-airport-ph", "geom:area": 0.0, "woe:scale": 19}}